{
   "project":{
      "id":2,
      "name":"Toyota Choices",
      "url":"http:\/\/www.toyotachoices.ae",
      "fields":[
         "Information Architecture",
         "Visual design",
         "Wireframes",
         "Behavioral design"
      ],
      "covers":{
         "404":"https:\/\/mir-cdn.behance.net\/v1\/rendition\/projects\/404\/475570.543e165802049.jpg"
      },
    
     
      "description":"Toyota Choices is the Personalised Contract Plan(PCP) of Toyota, the easiest way to drive a car you really want with attractive monthly payments. This Responsive website explain how the plan works in a unique digital experience that caters for desktop and mobile users. .",
      "modules":[
         {
            "id":2636362,
            "type":"image",
            "src":"img/toyotaChoices1.jpg",
            "width":960,
            "height":700,
            "sizes":[

            ]
         },
         {
            "id":2636362,
            "type":"image",
            "src":"img/toyotaChoices2.jpg",
            "width":960,
            "height":700,
            "sizes":[

            ]
         },
         {
            "id":2636362,
            "type":"image",
            "src":"img/toyotaChoices3.jpg",
            "width":960,
            "height":533,
            "sizes":[

            ]
         },
         {
            "id":2636362,
            "type":"image",
            "src":"img/toyotaChoices4.jpg",
            "width":960,
            "height":533,
            "sizes":[

            ]
         },
          {
            "id":2636362,
            "type":"image",
            "src":"img/toyotaChoices5.jpg",
            "width":960,
            "height":533,
            "sizes":[

            ]
         }
      ]
   },
   "http_code":200
}